text2mobi/__init__.py
text2mobi/converter.py
text2mobi-0.1.0.dist-info/DESCRIPTION.rst
text2mobi-0.1.0.dist-info/METADATA
text2mobi-0.1.0.dist-info/RECORD
text2mobi-0.1.0.dist-info/WHEEL
text2mobi-0.1.0.dist-info/metadata.json
text2mobi-0.1.0.dist-info/top_level.txt
