Metadata-Version: 2.0
Name: text2mobi
Version: 0.1.0
Summary: Convert text string or .txt/.html file to .mobi file for Amazon Kindle
Home-page: https://github.com/SouthpawGoblin/Text2Mobi
Author: Roger-Qi
Author-email: goblin-qyz@163.com
License: UNKNOWN
Keywords: text,kindle,ebook,mobi,convert
Platform: UNKNOWN
Requires-Dist: pyquery (>=1.2.17)
